lgl_getpubmed/__init__.py
lgl_getpubmed-3.0.dist-info/LICENSE
lgl_getpubmed-3.0.dist-info/METADATA
lgl_getpubmed-3.0.dist-info/WHEEL
lgl_getpubmed-3.0.dist-info/top_level.txt
lgl_getpubmed-3.0.dist-info/RECORD
