Metadata-Version: 2.1
Name: lgl-getpubmed
Version: 3.0
Summary: PubMed文献参考文献格式下载
Home-page: UNKNOWN
Author: liugeliang
Author-email: sx_liugeliang@163.com
License: UNKNOWN
Platform: UNKNOWN
Classifier: Programming Language :: Python :: 3
Classifier: License :: OSI Approved :: MIT License
Classifier: Operating System :: OS Independent
Requires-Python: >=3.6
License-File: LICENSE
